scripts/build_docs.py
scripts/serve_docs.py
warpconvnet/_C.cpython-312-x86_64-linux-gnu.so
warpconvnet/__init__.py
warpconvnet/constants.py
warpconvnet/types.py
warpconvnet/csrc/cub_sort.cu
warpconvnet/csrc/cutlass_gemm_gather_scatter.cu
warpconvnet/csrc/cutlass_gemm_gather_scatter_sm80_fp32.cu
warpconvnet/csrc/discrete_kernels.cu
warpconvnet/csrc/find_first_gt_bsearch.cu
warpconvnet/csrc/hash_serialization.cu
warpconvnet/csrc/hashmap_kernels.cu
warpconvnet/csrc/morton_code.cu
warpconvnet/csrc/sparse_conv.cu
warpconvnet/csrc/voxel_mapping_kernels.cu
warpconvnet/csrc/warpconvnet_pybind.cpp
warpconvnet/csrc/include/gemm_error_codes.h
warpconvnet/csrc/include/gemm_mma_tiles.h
warpconvnet/csrc/include/gemm_operation_interface.h
warpconvnet/csrc/include/gemm_operation_traits.h
warpconvnet/csrc/include/gemm_operation_types.h
warpconvnet/csrc/include/gemm_operations.h
warpconvnet/csrc/include/gemm_precision_traits.h
warpconvnet/csrc/include/helper.h
warpconvnet/dataset/modelnet.py
warpconvnet/dataset/scannet.py
warpconvnet/geometry/__init__.py
warpconvnet/geometry/base/__init__.py
warpconvnet/geometry/base/batched.py
warpconvnet/geometry/base/coords.py
warpconvnet/geometry/base/features.py
warpconvnet/geometry/base/geometry.py
warpconvnet/geometry/coords/__init__.py
warpconvnet/geometry/coords/grid.py
warpconvnet/geometry/coords/integer.py
warpconvnet/geometry/coords/real.py
warpconvnet/geometry/coords/sample.py
warpconvnet/geometry/coords/ops/batch_index.py
warpconvnet/geometry/coords/ops/expand.py
warpconvnet/geometry/coords/ops/grid.py
warpconvnet/geometry/coords/ops/sample.py
warpconvnet/geometry/coords/ops/serialization.py
warpconvnet/geometry/coords/ops/stride.py
warpconvnet/geometry/coords/ops/voxel.py
warpconvnet/geometry/coords/search/cache.py
warpconvnet/geometry/coords/search/continuous.py
warpconvnet/geometry/coords/search/hashmap.py
warpconvnet/geometry/coords/search/knn.py
warpconvnet-0.3.4.dist-info/METADATA
warpconvnet-0.3.4.dist-info/WHEEL
warpconvnet-0.3.4.dist-info/entry_points.txt
warpconvnet-0.3.4.dist-info/top_level.txt
warpconvnet-0.3.4.dist-info/RECORD
warpconvnet-0.3.4.dist-info/licenses/LICENSE.md
