Metadata-Version: 2.4
Name: warpconvnet
Version: 0.3.4
Summary: 3D Point Cloud and Spatially Sparse Convolutional Networks Framework
Author-email: Chris Choy <cchoy@nvidia.com>
Project-URL: GitHub, https://github.com/NVlabs/WarpConvNet
Project-URL: Documentation, https://nvlabs.github.io/WarpConvNet
Classifier: Programming Language :: Python :: 3.9
Classifier: Programming Language :: Python :: 3.10
Classifier: Programming Language :: Python :: 3.11
Classifier: Programming Language :: Python :: 3.12
Classifier: Programming Language :: Python :: 3.13
Classifier: License :: Other/Proprietary License
Classifier: Operating System :: OS Independent
Requires-Python: >=3.8
License-File: LICENSE.md
Requires-Dist: numpy
Requires-Dist: torch
Requires-Dist: warp-lang
Requires-Dist: jaxtyping
Requires-Dist: pybind11
Provides-Extra: flash-attn
Requires-Dist: flash-attn; extra == "flash-attn"
Provides-Extra: torch-scatter
Requires-Dist: torch-scatter; extra == "torch-scatter"
Provides-Extra: cuda11x
Requires-Dist: cupy-cuda11x; extra == "cuda11x"
Provides-Extra: cuda12x
Requires-Dist: cupy-cuda12x; extra == "cuda12x"
Provides-Extra: dev
Requires-Dist: ipdb; extra == "dev"
Requires-Dist: pre-commit; extra == "dev"
Requires-Dist: pytest; extra == "dev"
Requires-Dist: pytest-benchmark; extra == "dev"
Requires-Dist: pytest-cov; extra == "dev"
Provides-Extra: docs
Requires-Dist: mkdocs; extra == "docs"
Requires-Dist: mkdocs-material; extra == "docs"
Requires-Dist: mkdocstrings[python]; extra == "docs"
Requires-Dist: pymdown-extensions; extra == "docs"
Provides-Extra: models
Requires-Dist: rich; extra == "models"
Requires-Dist: h5py; extra == "models"
Requires-Dist: wandb; extra == "models"
Requires-Dist: hydra-core; extra == "models"
Requires-Dist: omegaconf; extra == "models"
Requires-Dist: lightning; extra == "models"
Requires-Dist: torchmetrics; extra == "models"
Provides-Extra: all
Requires-Dist: warpconvnet[dev]; extra == "all"
Requires-Dist: warpconvnet[docs]; extra == "all"
Requires-Dist: warpconvnet[models]; extra == "all"
Dynamic: license-file
Dynamic: requires-python
